copybook/__init__.py
copybook/abstract_field.py
copybook/copybook.py
copybook/field.py
copybook/field_group.py
copybook/parser.py
copybook-1.0.15.dist-info/LICENSE.txt
copybook-1.0.15.dist-info/METADATA
copybook-1.0.15.dist-info/WHEEL
copybook-1.0.15.dist-info/top_level.txt
copybook-1.0.15.dist-info/RECORD
