Metadata-Version: 2.1
Name: copybook
Version: 1.0.15
Summary: python copybook parser
Home-page: https://github.com/zalmane/copybook
Author: Oren Elias
Author-email: support@datayoga.io
License: MIT
Platform: UNKNOWN
Classifier: License :: OSI Approved :: MIT License
Classifier: Programming Language :: Python :: 3
Classifier: Programming Language :: Python :: 3.7
License-File: LICENSE.txt
Requires-Dist: pyparsing
